lama/__init__.py
lama/common.py
lama/current_commit
lama/monitor_memory.py
lama/paths.py
lama/version.py
lama/elastix/__init__.py
lama/elastix/deformations.py
lama/elastix/elastix_registration.py
lama/elastix/folding.py
lama/elastix/invert_transforms.py
lama/elastix/propagate_volumes.py
lama/elastix/reverse_registration.py
lama/img_processing/__init__.py
lama/img_processing/glcm3d.py
lama/img_processing/misc.py
lama/img_processing/normalise.py
lama/img_processing/normalise_background.py
lama/img_processing/organ_vol_calculation.py
lama/img_processing/read_minc.py
lama/lib/__init__.py
lama/lib/addict.py
lama/lib/transformations.py
lama/qc/__init__.py
lama/qc/collate_qc.py
lama/qc/common.py
lama/qc/folding.py
lama/qc/formatting.py
lama/qc/img_grid.py
lama/qc/interative_qc.py
lama/qc/metric_charts.py
lama/qc/organ_vol_plots.py
lama/qc/qc_images.py
lama/qc/roi_overlay.py
lama/registration_pipeline/__init__.py
lama/registration_pipeline/parallel_average.py
lama/registration_pipeline/parallel_average_pairwise.py
lama/registration_pipeline/run_lama.py
lama/registration_pipeline/validate_config.py
lama/registration_pipeline/optimise/__init__.py
lama/registration_pipeline/optimise/points.py
lama/registration_pipeline/optimise/regop_points.py
lama/registration_pipeline/optimise/run_lama_configs_grid.py
lama/registration_pipeline/optimise/test_regop.py
lama/scripts/__init__.py
lama/scripts/intensity_normalisation.py
lama/scripts/lama_get_test_data.py
lama/scripts/lama_get_walkthrough_data.py
lama/scripts/lama_job_runner.py
lama/scripts/lama_permutation_stats.py
lama/scripts/lama_reg.py
lama/scripts/lama_stats.py
lama/segmentation_plugins/__init__.py
lama/segmentation_plugins/plugin_interface.py
lama/segmentation_plugins/secondary_seg_lateral_ventricle.py
lama/segmentation_plugins/secondary_seg_lateral_ventricle_e145.py
lama/staging/__init__.py
lama/staging/affine_similarity_scaling_factors.py
lama/staging/baseline_selection.py
lama/staging/skeleton_length.py
lama_phenotype_detection-0.9.100.dist-info/LICENCE.md
lama_phenotype_detection-0.9.100.dist-info/METADATA
lama_phenotype_detection-0.9.100.dist-info/WHEEL
lama_phenotype_detection-0.9.100.dist-info/entry_points.txt
lama_phenotype_detection-0.9.100.dist-info/top_level.txt
lama_phenotype_detection-0.9.100.dist-info/RECORD
